paskell.py
paskell-0.1.0.dist-info/LICENSE
paskell-0.1.0.dist-info/METADATA
paskell-0.1.0.dist-info/WHEEL
paskell-0.1.0.dist-info/entry_points.txt
paskell-0.1.0.dist-info/top_level.txt
paskell-0.1.0.dist-info/RECORD
